countrings/__init__.py
countrings/__main__.py
countrings/countrings.py
countrings/countrings_nx.py
CountRings-0.1.7.dist-info/METADATA
CountRings-0.1.7.dist-info/WHEEL
CountRings-0.1.7.dist-info/entry_points.txt
CountRings-0.1.7.dist-info/top_level.txt
CountRings-0.1.7.dist-info/RECORD
