Metadata-Version: 2.1
Name: CountRings
Version: 0.1.7
Summary: Count rings in a graph.
Home-page: https://github.com/vitroid/CountRings/
Author: Masakazu Matsumoto
Author-email: vitroid@gmail.com
License: MIT
Keywords: countrings
Platform: UNKNOWN
Classifier: Development Status :: 4 - Beta
Classifier: Intended Audience :: Developers
Classifier: Programming Language :: Python
Classifier: Programming Language :: Python :: 3.5
Requires-Dist: networkx
Requires-Dist: methodtools
Requires-Dist: numpy
